{
    "configurations": [
        {
            "name": "Win32",
            "includePath": [
                "D:\\_Projektek\\_Kútklíma\\Arduino\\libraries\\OneWire",
                "D:\\_Projektek\\_Kútklíma\\Arduino\\libraries\\Utilities\\src",
                "C:\\Users\\fodor\\AppData\\Local\\Arduino15\\packages\\arduino\\tools\\**",
                "C:\\Users\\fodor\\AppData\\Local\\Arduino15\\packages\\arduino\\hardware\\avr\\1.8.2\\**",
                "D:\\_Projektek\\_Kútklíma\\Arduino\\libraries\\**"
            ],
            "forcedInclude": [
                "C:\\Users\\fodor\\AppData\\Local\\Arduino15\\packages\\arduino\\hardware\\avr\\1.8.2\\cores\\arduino\\Arduino.h"
            ],
            "intelliSenseMode": "gcc-x64",
            "compilerPath": "C:\\mingw-w64\\mingw32\\bin\\gcc.exe",
            "cStandard": "c11",
            "cppStandard": "c++17",
            "defines": [
                "USBCON"
            ]
        }
    ],
    "version": 4
}